iflow_mcp_slidev_mcp-0.1.2.dist-info/licenses/LICENSE
servers/__init__.py
servers/core/__init__.py
servers/core/base.py
servers/core/base_server.py
servers/core/common.py
servers/core/prompt_manager.py
servers/core/state_manager.py
servers/core/template_manager.py
servers/models/__init__.py
servers/models/prompt.py
servers/models/slidev.py
servers/models/template.py
servers/themes/academic/server.py
servers/themes/default/server.py
servers/themes/frankfurt/server.py
servers/themes/miracle/server.py
servers/themes/penguin/server.py
servers/themes/vuetiful/server.py
iflow_mcp_slidev_mcp-0.1.2.dist-info/METADATA
iflow_mcp_slidev_mcp-0.1.2.dist-info/WHEEL
iflow_mcp_slidev_mcp-0.1.2.dist-info/entry_points.txt
iflow_mcp_slidev_mcp-0.1.2.dist-info/top_level.txt
iflow_mcp_slidev_mcp-0.1.2.dist-info/RECORD
