Metadata-Version: 2.4
Name: iflow-mcp_slidev-mcp
Version: 0.1.2
Summary: A smart slide generator based on Slidev and LLM
Requires-Python: >=3.13
License-File: LICENSE
Requires-Dist: colorama>=0.4.6
Requires-Dist: crawl4ai>=0.7.0
Requires-Dist: jinja2>=3.1.6
Requires-Dist: mcp[cli]>=1.9.4
Requires-Dist: rich>=14.1.0
Requires-Dist: usermcp>=0.1.2
Dynamic: license-file
